bindtool/__init__.py
bindtool/bindtool.py
bindtool-1.5.0.dist-info/licenses/LICENSE
bindtool-1.5.0.dist-info/METADATA
bindtool-1.5.0.dist-info/WHEEL
bindtool-1.5.0.dist-info/entry_points.txt
bindtool-1.5.0.dist-info/top_level.txt
bindtool-1.5.0.dist-info/RECORD
