Metadata-Version: 2.4
Name: bindtool
Version: 1.5.0
Summary: Preprocessor for Bind9 zone files
Author-email: Peter Linss <peter@linss.com>
Project-URL: homepage, https://gitlab.linss.com/open-source/bindtool
Requires-Python: >=3.9
License-File: LICENSE
Requires-Dist: py3dns<5.0.0,>=3.1.0
Requires-Dist: pyasn1<2.0.0,>=0.4.5
Provides-Extra: ldap
Requires-Dist: python-ldap<4.0.0,>=3.2.0; extra == "ldap"
Provides-Extra: dev
Requires-Dist: types-PyYAML; extra == "dev"
Requires-Dist: types-setuptools; extra == "dev"
Requires-Dist: mypy; extra == "dev"
Requires-Dist: flake8; extra == "dev"
Requires-Dist: flake8-annotations; extra == "dev"
Requires-Dist: flake8-bandit; extra == "dev"
Requires-Dist: flake8-bugbear; extra == "dev"
Requires-Dist: flake8-commas; extra == "dev"
Requires-Dist: flake8-comprehensions; extra == "dev"
Requires-Dist: flake8-continuation; extra == "dev"
Requires-Dist: flake8-datetimez; extra == "dev"
Requires-Dist: flake8-docstrings; extra == "dev"
Requires-Dist: flake8-import-order; extra == "dev"
Requires-Dist: flake8-keyword-params; extra == "dev"
Requires-Dist: flake8-literal; extra == "dev"
Requires-Dist: flake8-modern-annotations; extra == "dev"
Requires-Dist: flake8-noqa; extra == "dev"
Requires-Dist: flake8-pyproject; extra == "dev"
Requires-Dist: flake8-requirements; extra == "dev"
Requires-Dist: flake8-typechecking-import; extra == "dev"
Requires-Dist: flake8-use-fstring; extra == "dev"
Requires-Dist: pep8-naming; extra == "dev"
Dynamic: license-file
